ghstatus/__init__.py
ghstatus/cli.py
ghstatus-0.3.2.data/data/LICENSE.txt
ghstatus-0.3.2.dist-info/DESCRIPTION.rst
ghstatus-0.3.2.dist-info/LICENSE.txt
ghstatus-0.3.2.dist-info/METADATA
ghstatus-0.3.2.dist-info/RECORD
ghstatus-0.3.2.dist-info/WHEEL
ghstatus-0.3.2.dist-info/entry_points.txt
ghstatus-0.3.2.dist-info/metadata.json
ghstatus-0.3.2.dist-info/top_level.txt
