Metadata-Version: 2.0
Name: ghstatus
Version: 0.3.2
Summary: GitHub commit status updater
Home-page: https://github.com/chickenzord/ghstatus
Author: Akhyar Amarullah
Author-email: akhyrul@gmail.com
License: MIT
Download-URL: https://github.com/chickenzord/ghstatus/archive/v0.3.2.tar.gz
Keywords: github,continuous-integration
Platform: UNKNOWN
Classifier: Development Status :: 4 - Beta
Classifier: License :: OSI Approved :: MIT License
Classifier: Intended Audience :: Developers
Classifier: Operating System :: POSIX :: Linux
Classifier: Programming Language :: Python
Classifier: Programming Language :: Python :: 2.7
Classifier: Programming Language :: Python :: 3.3
Classifier: Programming Language :: Python :: 3.4
Classifier: Programming Language :: Python :: 3.5
Classifier: Programming Language :: Python :: 3.6
Classifier: Topic :: Software Development :: Libraries
Classifier: Topic :: Utilities
Requires-Dist: click
Requires-Dist: dotenvy
Requires-Dist: requests
Requires-Dist: sh
